[
    {
        "id":"1",
        "titulo":"Impulso Inicial",
        "beneficio":[
            "Prioridad en tu categoria",
            "Ser recomendado en la pagina principal"
        ],
        "duracion":"Una Semana",
        "precio":100
    },
    {
        "id":"2",
        "titulo":"Impulso Constante",
        "beneficio":[
            "Prioridad en tu categoria",
            "Ser recomendado en la pagina principal"
        ],
        "duracion":"Un Mes",
        "precio":500
    },
    {
        "id":"3",
        "titulo":"Proyección Máxima",
        "beneficio":[
            "Prioridad en tu categoria",
            "Ser recomendado en la pagina principal"
        ],
        "duracion":"Un Año",
        "precio":10000
    }
]